MANIFEST.in
README.rst
setup.cfg
setup.py
deepsignal_plant/__init__.py
deepsignal_plant/_version.py
deepsignal_plant/call_modifications.py
deepsignal_plant/call_mods_freq.py
deepsignal_plant/dataloader.py
deepsignal_plant/deepsignal_plant.py
deepsignal_plant/denoise.py
deepsignal_plant/extract_features.py
deepsignal_plant/models.py
deepsignal_plant/train.py
deepsignal_plant.egg-info/PKG-INFO
deepsignal_plant.egg-info/SOURCES.txt
deepsignal_plant.egg-info/dependency_links.txt
deepsignal_plant.egg-info/entry_points.txt
deepsignal_plant.egg-info/not-zip-safe
deepsignal_plant.egg-info/requires.txt
deepsignal_plant.egg-info/top_level.txt
deepsignal_plant/utils/__init__.py
deepsignal_plant/utils/constants_torch.py
deepsignal_plant/utils/process_utils.py
deepsignal_plant/utils/ref_reader.py
deepsignal_plant/utils/txt_formater.py