Metadata-Version: 1.1
Name: deepsignal-plant
Version: 0.1.1
Summary: A deep-learning method for detecting DNA methylation state from Oxford Nanopore sequencing reads of plants
Home-page: https://github.com/PengNi/deepsignal-plant
Author: Peng Ni
Author-email: 543943952@qq.com
License: GNU General Public License v3 (GPLv3)
Download-URL: https://github.com/PengNi/deepsignal-plant/archive/0.1.1.tar.gz
Keywords: methylation,nanopore,neural network
Platform: any
Classifier: Programming Language :: Python :: 3
Classifier: Development Status :: 4 - Beta
Classifier: Natural Language :: English
Classifier: License :: OSI Approved :: GNU General Public License v3 (GPLv3)
Classifier: Operating System :: OS Independent
